py_hierarchy_2_2d/__init__.py
py_hierarchy_2_2d/parse.py
py_hierarchy_2_2d/tests/__init__.py
py_hierarchy_2_2d/tests/test_parse.py
py_hierarchy_2_2d/tests/utils.py
py_hierarchy_2_2d/util.py
py_hierarchy_2_2d-0.1.dist-info/WHEEL
py_hierarchy_2_2d-0.1.dist-info/METADATA
py_hierarchy_2_2d-0.1.dist-info/RECORD
